holonetra/__init__.py
holonetra/holonetra.py
holonetra-0.3.dist-info/LICENSE
holonetra-0.3.dist-info/METADATA
holonetra-0.3.dist-info/WHEEL
holonetra-0.3.dist-info/top_level.txt
holonetra-0.3.dist-info/RECORD
